{
  "entities": [
    {
      "light": {
        "enabled": true,
        "exposure": 0,
        "radius": 15.5,
        "outerDeg": 25,
        "intensity": 80,
        "innerDeg": 15,
        "color": [
          1,
          1,
          1
        ],
        "type": 2
      },
      "mesh": {
        "submeshes": [
          {
            "material": [
              0,
              1
            ],
            "type": 3,
            "name": "Light"
          }
        ]
      },
      "transform": {
        "s": [
          0.1,
          0.0999999,
          0.1
        ],
        "r": [
          0.797831,
          -0.108206,
          -0.547594,
          -0.22781
        ],
        "t": [
          -0.561412,
          2.44933,
          0.912417
        ]
      },
      "parent": null,
      "name": "Spot Light",
      "uuid": "1466536505412502712"
    },
    {
      "light": {
        "enabled": true,
        "exposure": 0,
        "radius": 0,
        "outerDeg": 25,
        "intensity": 5,
        "innerDeg": 15,
        "color": [
          1,
          0,
          0
        ],
        "type": 0
      },
      "mesh": {
        "submeshes": [
          {
            "material": [
              1,
              1
            ],
            "type": 3,
            "name": "Light"
          }
        ]
      },
      "transform": {
        "s": [
          0.1,
          0.1,
          0.1
        ],
        "r": [
          -0.23849,
          0.971145,
          0,
          0
        ],
        "t": [
          0,
          2,
          0
        ]
      },
      "parent": null,
      "name": "Directional Light",
      "uuid": "4443064496363746031"
    },
    {
      "mesh": {
        "submeshes": [
          {
            "material": [
              0,
              1
            ],
            "type": 1,
            "name": "Submesh 0"
          }
        ]
      },
      "transform": {
        "s": [
          31.6608,
          31.6608,
          31.6608
        ],
        "r": [
          1,
          0,
          0,
          0
        ],
        "t": [
          0,
          -1.64369,
          0
        ]
      },
      "parent": null,
      "name": "Plane",
      "uuid": "4831033614511398862"
    },
    {
      "mesh": {
        "submeshes": [
          {
            "material": [
              1,
              1
            ],
            "type": 0,
            "name": "Camera Body"
          }
        ]
      },
      "transform": {
        "s": [
          1,
          1,
          1
        ],
        "r": [
          0.999278,
          -0.0136536,
          -0.0354591,
          -0.000484496
        ],
        "t": [
          0.367007,
          2.16386,
          12.0363
        ]
      },
      "parent": null,
      "camera": {
        "exposure": 0,
        "farZ": 2000,
        "fovYDeg": 60,
        "nearZ": 0.01,
        "orthoHeight": 10,
        "projection": 0
      },
      "name": "Camera",
      "uuid": "8112557319220754979"
    },
    {
      "mesh": {
        "submeshes": [
          {
            "material": [
              0,
              1
            ],
            "type": 0,
            "name": "Submesh 0"
          }
        ]
      },
      "transform": {
        "s": [
          1,
          1,
          1
        ],
        "r": [
          1,
          0,
          0,
          0
        ],
        "t": [
          3.09196,
          0.366793,
          -0.0821544
        ]
      },
      "parent": null,
      "name": "Cube",
      "uuid": "11434800000000000000"
    },
    {
      "mesh": {
        "submeshes": [
          {
            "material": [
              1,
              1
            ],
            "type": 3,
            "name": "Submesh 0"
          }
        ]
      },
      "transform": {
        "s": [
          1,
          1,
          1
        ],
        "r": [
          1,
          0,
          0,
          0
        ],
        "t": [
          -1.18728,
          0,
          0
        ]
      },
      "parent": null,
      "name": "Sphere",
      "uuid": "14370200000000000000"
    },
    {
      "light": {
        "enabled": true,
        "exposure": 0,
        "radius": 8,
        "outerDeg": 25,
        "intensity": 80,
        "innerDeg": 15,
        "color": [
          1,
          1,
          1
        ],
        "type": 2
      },
      "mesh": {
        "submeshes": [
          {
            "material": [
              2,
              1
            ],
            "type": 3,
            "name": "Light"
          }
        ]
      },
      "transform": {
        "s": [
          0.1,
          0.1,
          0.1
        ],
        "r": [
          0.630774,
          -0.690639,
          0.221507,
          -0.275819
        ],
        "t": [
          0.774352,
          2,
          0
        ]
      },
      "parent": null,
      "name": "Spot Light",
      "uuid": "15604415598315951937"
    }
  ],
  "activeCamera": "8112557319220754979",
  "type": "NyxScene",
  "version": 2
}